{
  "beaches": [
    {
      "name": "Περαμά",
      "image": "images/beaches/Perama.png",
      "id": 1,
      "distance_km": 2,
      "location": "Βόρεια",
      "features": ["Αμμώδης", "Καθαρά νερά", "Οργανωμένη"],
      "crowd": "Ντόπιοι"
    },
    {
      "name": "Αχαράβη",
      "image": "images/beaches/acharavi.jpg",
      "id": 2,
      "distance_km": 4,
      "location": "Δυτικά",
      "features": ["Αμμώδης", "Καθαρά νερά", "Οργανωμένη"],
      "crowd": "Τουρίστες"
    },
    {
      "name": "Άγιος Γεώργιος Πάγων",
      "image": "images/beaches/agios_georgios_pagon.jpg",
      "id": 3,
      "distance_km": 6,
      "location": "Νοτιοανατολικά",
      "features": ["Αμμώδης", "Καθαρά νερά", "Οργανωμένη"],
      "crowd": "Ντόπιοι"
    },
    {
      "name": "Άγιος Γόρδιος",
      "image": "images/beaches/agios_gordios.jpg",
      "id": 4,
      "distance_km": 8,
      "location": "Δυτικά",
      "features": ["Αμμώδης", "Καθαρά νερά", "Οργανωμένη"],
      "crowd": "Τουρίστες"
    },
    {
      "name": "Άγιος Ιωάννης",
      "image": "images/beaches/agios_ioannis.jpg",
      "id": 5,
      "distance_km": 10,
      "location": "Βόρεια",
      "features": ["Αμμώδης", "Καθαρά νερά", "Οργανωμένη"],
      "crowd": "Ντόπιοι"
    },
    {
      "name": "Άγιος Στέφανος",
      "image": "images/beaches/agios_stefanos.jpg",
      "id": 6,
      "distance_km": 12,
      "location": "Νοτιοανατολικά",
      "features": ["Αμμώδης", "Καθαρά νερά", "Οργανωμένη"],
      "crowd": "Τουρίστες"
    },
    {
      "name": "Άγιος Στέφανος (Βορράς)",
      "image": "images/beaches/agios_stefanos_north.jpg",
      "id": 7,
      "distance_km": 14,
      "location": "Βόρεια",
      "features": ["Αμμώδης", "Καθαρά νερά", "Οργανωμένη"],
      "crowd": "Ντόπιοι"
    },
    {
      "name": "Άγιος Στέφανος Πάγοι",
      "image": "images/beaches/agios_stefanos_pagi.jpg",
      "id": 8,
      "distance_km": 16,
      "location": "Δυτικά",
      "features": ["Αμμώδης", "Καθαρά νερά", "Οργανωμένη"],
      "crowd": "Τουρίστες"
    },
    {
      "name": "Άγνι",
      "image": "images/beaches/agni.jpg",
      "id": 9,
      "distance_km": 18,
      "location": "Νοτιοανατολικά",
      "features": ["Αμμώδης", "Καθαρά νερά", "Οργανωμένη"],
      "crowd": "Ντόπιοι"
    },
    {
      "name": "Αρίλλας",
      "image": "images/beaches/arillas.jpg",
      "id": 10,
      "distance_km": 20,
      "location": "Δυτικά",
      "features": ["Αμμώδης", "Καθαρά νερά", "Οργανωμένη"],
      "crowd": "Τουρίστες"
    },
    {
      "name": "Μπαρμπάτι",
      "image": "images/beaches/barmpati.jpg",
      "id": 11,
      "distance_km": 22,
      "location": "Βόρεια",
      "features": ["Αμμώδης", "Καθαρά νερά", "Οργανωμένη"],
      "crowd": "Ντόπιοι"
    },
    {
      "name": "Μπενίτσες",
      "image": "images/beaches/benitses.jpg",
      "id": 12,
      "distance_km": 24,
      "location": "Νοτιοανατολικά",
      "features": ["Αμμώδης", "Καθαρά νερά", "Οργανωμένη"],
      "crowd": "Τουρίστες"
    },
    {
      "name": "Canal d'Amour",
      "image": "images/beaches/canal_damour.jpg",
      "id": 13,
      "distance_km": 26,
      "location": "Βόρεια",
      "features": ["Αμμώδης", "Καθαρά νερά", "Οργανωμένη"],
      "crowd": "Ντόπιοι"
    },
    {
      "name": "Κανάλι του Έρωτα",
      "image": "images/beaches/canal_erotas.jpg",
      "id": 14,
      "distance_km": 28,
      "location": "Δυτικά",
      "features": ["Αμμώδης", "Καθαρά νερά", "Οργανωμένη"],
      "crowd": "Τουρίστες"
    },
    {
      "name": "Δασσιά",
      "image": "images/beaches/dassia.jpg",
      "id": 15,
      "distance_km": 30,
      "location": "Νοτιοανατολικά",
      "features": ["Αμμώδης", "Καθαρά νερά", "Οργανωμένη"],
      "crowd": "Ντόπιοι"
    },
    {
      "name": "Γλυφάδα",
      "image": "images/beaches/glyfada.jpg",
      "id": 16,
      "distance_km": 32,
      "location": "Δυτικά",
      "features": ["Αμμώδης", "Καθαρά νερά", "Οργανωμένη"],
      "crowd": "Τουρίστες"
    },
    {
      "name": "Χαλικούνας",
      "image": "images/beaches/halikounas.jpg",
      "id": 17,
      "distance_km": 34,
      "location": "Βόρεια",
      "features": ["Αμμώδης", "Καθαρά νερά", "Οργανωμένη"],
      "crowd": "Ντόπιοι"
    },
    {
      "name": "Ίσσος",
      "image": "images/beaches/issos.jpg",
      "id": 18,
      "distance_km": 36,
      "location": "Νοτιοανατολικά",
      "features": ["Αμμώδης", "Καθαρά νερά", "Οργανωμένη"],
      "crowd": "Τουρίστες"
    },
    {
      "name": "Καλάμι",
      "image": "images/beaches/kalami.jpg",
      "id": 19,
      "distance_km": 38,
      "location": "Βόρεια",
      "features": ["Αμμώδης", "Καθαρά νερά", "Οργανωμένη"],
      "crowd": "Ντόπιοι"
    },
    {
      "name": "Καρδάκι",
      "image": "images/beaches/kardaki.jpg",
      "id": 20,
      "distance_km": 40,
      "location": "Δυτικά",
      "features": ["Αμμώδης", "Καθαρά νερά", "Οργανωμένη"],
      "crowd": "Τουρίστες"
    },
    {
      "name": "Κομμένο",
      "image": "images/beaches/kommeno.jpg",
      "id": 21,
      "distance_km": 42,
      "location": "Νοτιοανατολικά",
      "features": ["Αμμώδης", "Ήσυχη", "Οικογενειακή"],
      "crowd": "Ντόπιοι"
    },
    {
      "name": "Κοντόκαλι",
      "image": "images/beaches/kontokali.jpg",
      "id": 22,
      "distance_km": 44,
      "location": "Δυτικά",
      "features": ["Αμμώδης", "Οργανωμένη", "Προσβάσιμη"],
      "crowd": "Τουρίστες"
    },
    {
      "name": "Κουλούρα",
      "image": "images/beaches/kouloura.jpg",
      "id": 23,
      "distance_km": 46,
      "location": "Νοτιοανατολικά",
      "features": ["Πέτρινη", "Καθαρά νερά", "Γραφική"],
      "crowd": "Ντόπιοι"
    },
    {
      "name": "Λογγάς",
      "image": "images/beaches/loggas.jpg",
      "id": 24,
      "distance_km": 48,
      "location": "Βόρεια",
      "features": ["Γκρεμός", "Ηλιοβασίλεμα", "Θέα"],
      "crowd": "Ρομαντικοί επισκέπτες"
    },
    {
      "name": "Μαραθιάς",
      "image": "images/beaches/marathias.jpg",
      "id": 25,
      "distance_km": 50,
      "location": "Νότια",
      "features": ["Αμμουδιά", "Μεγάλο μήκος", "Ησυχία"],
      "crowd": "Λίγοι"
    },
    {
      "name": "Μεσογγή",
      "image": "images/beaches/messonghi.jpg",
      "id": 26,
      "distance_km": 52,
      "location": "Νοτιοανατολικά",
      "features": ["Οικογενειακή", "Οργανωμένη", "Ρηχά νερά"],
      "crowd": "Οικογένειες"
    },
    {
      "name": "Μυρτιώτισσα",
      "image": "images/beaches/myrtiotissa.jpg",
      "id": 27,
      "distance_km": 54,
      "location": "Δυτικά",
      "features": ["Γυμνιστών", "Απόκρημνη", "Αυθεντική"],
      "crowd": "Εναλλακτικοί"
    },
    {
      "name": "Παραμόνα",
      "image": "images/beaches/paramona.jpg",
      "id": 28,
      "distance_km": 56,
      "location": "Νοτιοδυτικά",
      "features": ["Απομονωμένη", "Πευκόφυτη", "Αμμουδιά"],
      "crowd": "Ζευγάρια"
    },
    {
      "name": "Παλαιοκαστρίτσα",
      "image": "images/beaches/palaiokastritsa.jpg",
      "id": 29,
      "distance_km": 58,
      "location": "Δυτικά",
      "features": ["Γραφική", "Διαυγή νερά", "Μοναστήρι"],
      "crowd": "Όλοι"
    },
    {
      "name": "Ρόδα",
      "image": "images/beaches/roda.jpg",
      "id": 30,
      "distance_km": 60,
      "location": "Βόρεια",
      "features": ["Οργανωμένη", "Μικρά κύματα", "Ανάμεικτο κοινό"],
      "crowd": "Ντόπιοι & Τουρίστες"
    },
    {
      "name": "Σιδάρι",
      "image": "images/beaches/sidari.jpg",
      "id": 31,
      "distance_km": 62,
      "location": "Βορειοδυτικά",
      "features": ["Γνωστό θέρετρο", "Αμμουδιά", "Ζωντάνια"],
      "crowd": "Πολύς κόσμος"
    }
  ]
}
